whisperEngine/__init__.py
whisperEngine/whisperEngine.py
whisperEngine-1.0.0.dist-info/LICENSE.txt
whisperEngine-1.0.0.dist-info/METADATA
whisperEngine-1.0.0.dist-info/WHEEL
whisperEngine-1.0.0.dist-info/top_level.txt
whisperEngine-1.0.0.dist-info/RECORD
