Metadata-Version: 2.1
Name: whisperEngine
Version: 1.0.0
Summary: whisper engine package
Home-page: https://github.com/pypa/sampleproject
Author: VirginMariaJeremia
Author-email: VirginMariaJeremia@gmail.com
Classifier: Programming Language :: Python :: 3
Classifier: License :: OSI Approved :: MIT License
Classifier: Operating System :: OS Independent
License-File: LICENSE.txt
